zonoopt/__init__.py
zonoopt/__init__.pyi
zonoopt/_core.cp310-win_amd64.pyd
zonoopt/_core.pyi
zonoopt/zono_plot.py
zonoopt-2.0.1.dist-info/METADATA
zonoopt-2.0.1.dist-info/WHEEL
zonoopt-2.0.1.dist-info/licenses/LICENSE
zonoopt-2.0.1.dist-info/RECORD
