Metadata-Version: 2.2
Name: zonoopt
Version: 2.0.1
Summary: Python bindings for the ZonoOpt C++ library
Author-Email: Joshua Robbins <jrobbins@psu.edu>
Classifier: Development Status :: 4 - Beta
Classifier: License :: OSI Approved :: MIT License
Classifier: Programming Language :: Python :: 3 :: Only
Classifier: Programming Language :: Python :: 3.7
Classifier: Programming Language :: Python :: 3.8
Classifier: Programming Language :: Python :: 3.9
Classifier: Programming Language :: Python :: 3.10
Classifier: Programming Language :: Python :: 3.11
Classifier: Programming Language :: Python :: 3.12
Classifier: Programming Language :: Python :: 3.13
Requires-Python: >=3.9
Requires-Dist: matplotlib>=3.6
Requires-Dist: numpy
Requires-Dist: scipy
